storeyloss/__init__.py
storeyloss/models.py
storeyloss/slf.py
storeyloss/slf_gui.py
storeyloss-1.1.3.dist-info/METADATA
storeyloss-1.1.3.dist-info/WHEEL
storeyloss-1.1.3.dist-info/top_level.txt
storeyloss-1.1.3.dist-info/RECORD
