Metadata-Version: 2.1
Name: storeyloss
Version: 1.1.3
Summary: Storey-loss function generator to be used in loss assessment.
Home-page: https://github.com/davitshahnazaryan3/SLFGenerator
Author: Davit Shahnazaryan
Author-email: shahnazaryandavit1@gmail.com
License: GPL-3.0
Project-URL: Bug Tracker, https://github.com/davitshahnazaryan3/SLFGenerator/issues
Classifier: License :: OSI Approved :: GNU General Public License v3 (GPLv3)
Classifier: Operating System :: OS Independent
Classifier: Programming Language :: Python :: 3
Classifier: Programming Language :: Python :: 3 :: Only
Requires-Python: >=3.9
Requires-Dist: numpy ~=1.25.2
Requires-Dist: pandas ~=2.0.3
Requires-Dist: scipy ~=1.11.2
Requires-Dist: pillow ~=10.0.0
Requires-Dist: future ~=0.18.3
Requires-Dist: matplotlib ~=3.7.2
Requires-Dist: pydantic ~=1.10.4
Provides-Extra: dev
Requires-Dist: pytest ~=7.4.0 ; extra == 'dev'
Requires-Dist: flake8 ~=6.1.0 ; extra == 'dev'
